jas/__init__.py
jas/bitstream.py
jas/cli.py
jas/compressor.py
jas/decompressor.py
jas/huffman.py
jas/structured.py
jas/tokenizer.py
jas/tokenizer_v1.py
jas/utils.py
jas_compression-1.0.0.dist-info/LICENSE
jas_compression-1.0.0.dist-info/METADATA
jas_compression-1.0.0.dist-info/WHEEL
jas_compression-1.0.0.dist-info/top_level.txt
jas_compression-1.0.0.dist-info/RECORD
