Metadata-Version: 2.1
Name: jas-compression
Version: 1.0.0
Summary: A custom text compression library using tokenization and Huffman encoding.
Home-page: https://github.com/JasTandon/jas-compression
Author: Jas Tandon
Author-email: jastandon@icloud.com
Classifier: Programming Language :: Python :: 3
Classifier: License :: OSI Approved :: MIT License
Classifier: Operating System :: OS Independent
Requires-Python: >=3.6
License-File: LICENSE
Requires-Dist: tqdm
Requires-Dist: PyYAML
